[{
    "student_name": "Palesa Mashiyane",
    "email": "palesa.mashiyane@somewhere.com",
    "grade": 7,
    "section": null,
    "activity_date": "2016-11-17T22:00:00.000Z",
    "points": 28635
}, {
    "student_name": "Minenhle Ntombela",
    "email": "minenhle.ntombela@somewhere.com",
    "grade": 7,
    "section": null,
    "activity_date": "2016-11-17T22:00:00.000Z",
    "points": 69715
}, {
    "student_name": "Tanaka Muzerengani",
    "email": "tanaka.muzerengani@somewhere.com",
    "grade": 7,
    "section": null,
    "activity_date": "2016-11-17T22:00:00.000Z",
    "points": 170765
}, {
    "student_name": "Senzo Mbatha",
    "email": "senzo.mbatha@somewhere.com",
    "grade": 7,
    "section": null,
    "activity_date": "2016-11-16T22:00:00.000Z",
    "points": 68275
}, {
    "student_name": "Andile Jele",
    "email": "andile.jele@somewhere.com",
    "grade": 7,
    "section": null,
    "activity_date": "2016-11-17T22:00:00.000Z",
    "points": 65642
}, {
    "student_name": "Thandolwethu Raditsela",
    "email": "thandolwethu.raditsela@somewhere.com",
    "grade": 7,
    "section": null,
    "activity_date": "2016-11-17T22:00:00.000Z",
    "points": 52895
}, {
    "student_name": "Gugu Nhlengethwa",
    "email": "gugu.nhlengethwa@somewhere.com",
    "grade": 7,
    "section": null,
    "activity_date": "2016-11-17T22:00:00.000Z",
    "points": 131176
}, {
    "student_name": "Noluthando Mathebula",
    "email": "noluthando.mathebula@somewhere.com",
    "grade": 7,
    "section": null,
    "activity_date": "2016-11-30T22:00:00.000Z",
    "points": 67075
}, {
    "student_name": "Chantal Matekane",
    "email": "chantal.matekane@somewhere.com",
    "grade": 7,
    "section": null,
    "activity_date": "2016-11-17T22:00:00.000Z",
    "points": 40815
}, {
    "student_name": "Njabulo Ngwenya",
    "email": "njabulo.ngwenya@somewhere.com",
    "grade": 7,
    "section": null,
    "activity_date": "2016-11-17T22:00:00.000Z",
    "points": 54160
}, {
    "student_name": "Noluvuyo Gawula",
    "email": "noluvuyo.gawula@somewhere.com",
    "grade": 7,
    "section": null,
    "activity_date": "2016-11-30T22:00:00.000Z",
    "points": 14390
}, {
    "student_name": "Mduduzi Sjula",
    "email": "mduduzi.sjula@somewhere.com",
    "grade": 7,
    "section": null,
    "activity_date": "2016-11-16T22:00:00.000Z",
    "points": 59486
}, {
    "student_name": "Nonhlanhla Mphange",
    "email": "nonhlanhla.mphange@somewhere.com",
    "grade": 7,
    "section": null,
    "activity_date": "2016-11-17T22:00:00.000Z",
    "points": 102740
}, {
    "student_name": "Naledi Foramau",
    "email": "naledi.foramau@somewhere.com",
    "grade": 7,
    "section": null,
    "activity_date": "2016-11-17T22:00:00.000Z",
    "points": 49305
}, {
    "student_name": "Humbelani Netshiomba",
    "email": "humbelani.netshiomba@somewhere.com",
    "grade": 7,
    "section": null,
    "activity_date": "2016-11-17T22:00:00.000Z",
    "points": 107367
}, {
    "student_name": "Dube Sandile",
    "email": "dube.sandile@somewhere.com",
    "grade": 7,
    "section": null,
    "activity_date": "2016-11-30T22:00:00.000Z",
    "points": 69546
}, {
    "student_name": "Amogelang Matshane",
    "email": "amogelang.matshane@somewhere.com",
    "grade": 7,
    "section": null,
    "activity_date": "2016-11-30T22:00:00.000Z",
    "points": 51175
}, {
    "student_name": "Nhlanhla Buthelezi",
    "email": "nhlanhla.buthelezi@somewhere.com",
    "grade": 7,
    "section": null,
    "activity_date": "2016-11-17T22:00:00.000Z",
    "points": 42482
}, {
    "student_name": "Nabo Msiza",
    "email": "nabo.msiza@somewhere.com",
    "grade": 7,
    "section": null,
    "activity_date": "2016-11-17T22:00:00.000Z",
    "points": 60125
}, {
    "student_name": "Thulisile Mahlangu",
    "email": "thulisile.mahlangu@somewhere.com",
    "grade": 7,
    "section": null,
    "activity_date": "2016-11-17T22:00:00.000Z",
    "points": 46377
}, {
    "student_name": "Khanyisile Ntshangase",
    "email": "khanyisile.ntshangase@somewhere.com",
    "grade": 7,
    "section": null,
    "activity_date": "2016-11-17T22:00:00.000Z",
    "points": 77370
}, {
    "student_name": "Bridget Skosana",
    "email": "bridget.skosana@somewhere.com",
    "grade": 7,
    "section": null,
    "activity_date": "2016-11-30T22:00:00.000Z",
    "points": 107860
}, {
    "student_name": "Simphiwe Shabalala",
    "email": "simphiwe.shabalala@somewhere.com",
    "grade": 7,
    "section": null,
    "activity_date": "2016-11-17T22:00:00.000Z",
    "points": 108945
}, {
    "student_name": "Tracy Motaung",
    "email": "tracy.motaung@somewhere.com",
    "grade": 7,
    "section": null,
    "activity_date": "2016-11-17T22:00:00.000Z",
    "points": 46345
}, {
    "student_name": "Oratile Moema",
    "email": "oratile.moema@somewhere.com",
    "grade": 7,
    "section": null,
    "activity_date": "2016-11-17T22:00:00.000Z",
    "points": 124700
}, {
    "student_name": "Katlego Kgomo",
    "email": "katlego.kgomo@somewhere.com",
    "grade": 7,
    "section": null,
    "activity_date": "2016-11-30T22:00:00.000Z",
    "points": 105295
}, {
    "student_name": "Nkululeko Dyantji",
    "email": "nkululeko.dyantji@somewhere.com",
    "grade": 7,
    "section": null,
    "activity_date": "2016-11-17T22:00:00.000Z",
    "points": 107216
}, {
    "student_name": "Neo Masuku",
    "email": "neo.masuku@somewhere.com",
    "grade": 7,
    "section": null,
    "activity_date": "2016-11-30T22:00:00.000Z",
    "points": 68485
}, {
    "student_name": "Ellen Tivane",
    "email": "ellen.tivane@somewhere.com",
    "grade": 7,
    "section": null,
    "activity_date": "2016-11-17T22:00:00.000Z",
    "points": 54235
}, {
    "student_name": "Thato Padi",
    "email": "thato.padi@somewhere.com",
    "grade": 7,
    "section": null,
    "activity_date": "2016-11-17T22:00:00.000Z",
    "points": 59845
}, {
    "student_name": "Thembelihle Guliwe",
    "email": "thembelihle.guliwe@somewhere.com",
    "grade": 7,
    "section": null,
    "activity_date": "2016-11-17T22:00:00.000Z",
    "points": 48170
}, {
    "student_name": "Dineo Masondo",
    "email": "dineo.masondo@somewhere.com",
    "grade": 7,
    "section": null,
    "activity_date": "2016-11-30T22:00:00.000Z",
    "points": 95405
}, {
    "student_name": "Mandisa Mahlangu",
    "email": "mandisa.mahlangu@somewhere.com",
    "grade": 7,
    "section": null,
    "activity_date": "2016-11-30T22:00:00.000Z",
    "points": 57548
}, {
    "student_name": "Thakgatso Ramaila",
    "email": "thakgatso.ramaila@somewhere.com",
    "grade": 7,
    "section": null,
    "activity_date": "2016-11-17T22:00:00.000Z",
    "points": 112948
}, {
    "student_name": "Xiluva Poli",
    "email": "xiluva.poli@somewhere.com",
    "grade": 7,
    "section": null,
    "activity_date": "2016-11-17T22:00:00.000Z",
    "points": 67454
}, {
    "student_name": "Gift Letuka",
    "email": "gift.letuka@somewhere.com",
    "grade": 7,
    "section": null,
    "activity_date": "2016-11-19T22:00:00.000Z",
    "points": 118497
}, {
    "student_name": "Precious Tsagane",
    "email": "precious.tsagane@somewhere.com",
    "grade": 7,
    "section": null,
    "activity_date": "2016-11-17T22:00:00.000Z",
    "points": 58580
}, {
    "student_name": "Zinhle Skhosana",
    "email": "zinhle.skhosana@somewhere.com",
    "grade": 7,
    "section": null,
    "activity_date": "2016-11-17T22:00:00.000Z",
    "points": 16986
}, {
    "student_name": "Ntombikayise Mkhwanazi",
    "email": "ntombikayise.mkhwanazi@somewhere.com",
    "grade": 7,
    "section": null,
    "activity_date": "2016-11-17T22:00:00.000Z",
    "points": 71905
}, {
    "student_name": "Thulani Sibanyoni",
    "email": "thulani.sibanyoni@somewhere.com",
    "grade": 7,
    "section": null,
    "activity_date": "2016-11-17T22:00:00.000Z",
    "points": 52130
}, {
    "student_name": "Gugu Ndaba",
    "email": "gugu.ndaba@somewhere.com",
    "grade": 7,
    "section": null,
    "activity_date": "2016-11-17T22:00:00.000Z",
    "points": 161915
}, {
    "student_name": "Kelethabo Molefe",
    "email": "kelethabo.molefe@somewhere.com",
    "grade": 7,
    "section": null,
    "activity_date": "2016-11-17T22:00:00.000Z",
    "points": 105337
}, {
    "student_name": "Ntsako Bazima",
    "email": "ntsako.bazima@somewhere.com",
    "grade": 7,
    "section": null,
    "activity_date": "2016-11-17T22:00:00.000Z",
    "points": 37705
}, {
    "student_name": "Nontobeko Msibi",
    "email": "nontobeko.msibi@somewhere.com",
    "grade": 7,
    "section": null,
    "activity_date": "2016-10-31T22:00:00.000Z",
    "points": 6130
}, {
    "student_name": "Gugu Msimango",
    "email": "gugu.msimango@somewhere.com",
    "grade": 7,
    "section": null,
    "activity_date": "2016-11-30T22:00:00.000Z",
    "points": 110620
}, {
    "student_name": "Kethabile Molefe",
    "email": "kethabile.molefe@somewhere.com",
    "grade": 7,
    "section": null,
    "activity_date": "2016-11-17T22:00:00.000Z",
    "points": 74483
}, {
    "student_name": "Mesuli Ndiyaza",
    "email": "mesuli.ndiyaza@somewhere.com",
    "grade": 7,
    "section": null,
    "activity_date": "2016-11-17T22:00:00.000Z",
    "points": 239160
}, {
    "student_name": "Mxolisi Msomi",
    "email": "mxolisi.msomi@somewhere.com",
    "grade": 7,
    "section": null,
    "activity_date": "2016-11-17T22:00:00.000Z",
    "points": 118323
}, {
    "student_name": "Reneiloe Noga",
    "email": "reneiloe.noga@somewhere.com",
    "grade": 7,
    "section": null,
    "activity_date": "2016-11-17T22:00:00.000Z",
    "points": 54060
}, {
    "student_name": "Lebohang1 Ndlovu",
    "email": "lebohang1.ndlovu@somewhere.com",
    "grade": 7,
    "section": null,
    "activity_date": "2016-11-30T22:00:00.000Z",
    "points": 61000
}, {
    "student_name": "Karabo Kokong",
    "email": "karabo.kokong@somewhere.com",
    "grade": 7,
    "section": null,
    "activity_date": "2016-11-17T22:00:00.000Z",
    "points": 68325
}, {
    "student_name": "Snenhlanhla Sibiya",
    "email": "snenhlanhla.sibiya@somewhere.com",
    "grade": 7,
    "section": null,
    "activity_date": "2016-11-17T22:00:00.000Z",
    "points": 80680
}, {
    "student_name": "Mahlompho Molekane",
    "email": "mahlompho.molekane@somewhere.com",
    "grade": 7,
    "section": null,
    "activity_date": "2016-11-17T22:00:00.000Z",
    "points": 10930
}, {
    "student_name": "Ntokozo Mahlangu",
    "email": "ntokozo.mahlangu@somewhere.com",
    "grade": 7,
    "section": null,
    "activity_date": "2016-11-17T22:00:00.000Z",
    "points": 75269
}, {
    "student_name": "Siphokazi Nhlapo",
    "email": "siphokazi.nhlapo@somewhere.com",
    "grade": 7,
    "section": null,
    "activity_date": "2016-11-17T22:00:00.000Z",
    "points": 57555
}, {
    "student_name": "Neliswa Thusini",
    "email": "neliswa.thusini@somewhere.com",
    "grade": 7,
    "section": null,
    "activity_date": "2016-11-30T22:00:00.000Z",
    "points": 92814
}, {
    "student_name": "Kopano Makolane",
    "email": "kopano.makolane@somewhere.com",
    "grade": 7,
    "section": null,
    "activity_date": "2016-11-17T22:00:00.000Z",
    "points": 17610
}, {
    "student_name": "Malekutu Chego",
    "email": "malekutu.chego@somewhere.com",
    "grade": 7,
    "section": null,
    "activity_date": "2016-11-17T22:00:00.000Z",
    "points": 24357
}, {
    "student_name": "Tshepo Busakwe",
    "email": "tshepo.busakwe@somewhere.com",
    "grade": 7,
    "section": null,
    "activity_date": "2016-11-17T22:00:00.000Z",
    "points": 63244
}, {
    "student_name": "Duduzile Nkabinde",
    "email": "duduzile.nkabinde@somewhere.com",
    "grade": 7,
    "section": null,
    "activity_date": "2016-11-30T22:00:00.000Z",
    "points": 150633
}, {
    "student_name": "Luyanda Nkosi",
    "email": "luyanda.nkosi@somewhere.com",
    "grade": 7,
    "section": null,
    "activity_date": "2016-11-17T22:00:00.000Z",
    "points": 124375
}, {
    "student_name": "Zamokuhle Mkhwanazi",
    "email": "zamokuhle.mkhwanazi@somewhere.com",
    "grade": 7,
    "section": null,
    "activity_date": "2016-11-16T22:00:00.000Z",
    "points": 67955
}, {
    "student_name": "Katlego Makoe",
    "email": "katlego.makoe@somewhere.com",
    "grade": 7,
    "section": null,
    "activity_date": "2016-11-30T22:00:00.000Z",
    "points": 57790
}, {
    "student_name": "Masego Mabena",
    "email": "masego.mabena@somewhere.com",
    "grade": 7,
    "section": null,
    "activity_date": "2016-11-18T22:00:00.000Z",
    "points": 101330
}, {
    "student_name": "Calvin Mtsweni",
    "email": "calvin.mtsweni@somewhere.com",
    "grade": 7,
    "section": null,
    "activity_date": "2016-11-17T22:00:00.000Z",
    "points": 44600
}, {
    "student_name": "Dineo Sekgololo",
    "email": "dineo.sekgololo@somewhere.com",
    "grade": 7,
    "section": null,
    "activity_date": "2016-11-17T22:00:00.000Z",
    "points": 28472
}, {
    "student_name": "Musawenkosi Nkabinde",
    "email": "musawenkosi.nkabinde@somewhere.com",
    "grade": 7,
    "section": null,
    "activity_date": "2016-11-30T22:00:00.000Z",
    "points": 35733
}, {
    "student_name": "Nompumelelo Zikalala",
    "email": "nompumelelo.zikalala@somewhere.com",
    "grade": 7,
    "section": null,
    "activity_date": "2016-11-17T22:00:00.000Z",
    "points": 33715
}, {
    "student_name": "Siyabonga Nkosi",
    "email": "siyabonga.nkosi@somewhere.com",
    "grade": 7,
    "section": null,
    "activity_date": "2016-11-17T22:00:00.000Z",
    "points": 110270
}, {
    "student_name": "Koketso Matshane",
    "email": "koketso.matshane@somewhere.com",
    "grade": 7,
    "section": null,
    "activity_date": "2016-11-17T22:00:00.000Z",
    "points": 48235
}, {
    "student_name": "Karabogr7 Ralefeta",
    "email": "karabogr7.ralefeta@somewhere.com",
    "grade": 7,
    "section": null,
    "activity_date": "2016-11-17T22:00:00.000Z",
    "points": 118122
}, {
    "student_name": "Bathule Khulu",
    "email": "bathule.khulu@somewhere.com",
    "grade": 7,
    "section": null,
    "activity_date": "2016-11-17T22:00:00.000Z",
    "points": 50260
}, {
    "student_name": "Tshepo Lebaka",
    "email": "tshepo.lebaka@somewhere.com",
    "grade": 7,
    "section": null,
    "activity_date": "2016-11-17T22:00:00.000Z",
    "points": 59500
}, {
    "student_name": "Khethiwe Mthenjwa",
    "email": "khethiwe.mthenjwa@somewhere.com",
    "grade": 7,
    "section": null,
    "activity_date": "2016-11-30T22:00:00.000Z",
    "points": 106240
}, {
    "student_name": "Silindokuhle Thwala",
    "email": "silindokuhle.thwala@somewhere.com",
    "grade": 7,
    "section": null,
    "activity_date": "2016-11-13T22:00:00.000Z",
    "points": 56782
}, {
    "student_name": "Tumelo Tsotetsi",
    "email": "tumelo.tsotetsi@somewhere.com",
    "grade": 7,
    "section": null,
    "activity_date": "2016-11-17T22:00:00.000Z",
    "points": 46685
}, {
    "student_name": "Sonwabile Makofane",
    "email": "sonwabile.makofane@somewhere.com",
    "grade": 7,
    "section": null,
    "activity_date": "2016-11-16T22:00:00.000Z",
    "points": 67461
}, {
    "student_name": "Prince Bottoman",
    "email": "prince.bottoman@somewhere.com",
    "grade": 7,
    "section": null,
    "activity_date": "2016-11-30T22:00:00.000Z",
    "points": 174115
}, {
    "student_name": "Anovuyo1 Kapayi",
    "email": "anovuyo1.kapayi@somewhere.com",
    "grade": 7,
    "section": null,
    "activity_date": "2016-11-14T22:00:00.000Z",
    "points": 37490
}, {
    "student_name": "Itumeleng Lephoto",
    "email": "itumeleng.lephoto@somewhere.com",
    "grade": 7,
    "section": null,
    "activity_date": "2016-11-30T22:00:00.000Z",
    "points": 35880
}, {
    "student_name": "Zibuthe Vuzane",
    "email": "zibuthe.vuzane@somewhere.com",
    "grade": 8,
    "section": null,
    "activity_date": "2016-11-10T22:00:00.000Z",
    "points": 2900
}, {
    "student_name": "Sthembele Majola",
    "email": "sthembele.majola@somewhere.com",
    "grade": 9,
    "section": null,
    "activity_date": "2016-10-27T22:00:00.000Z",
    "points": 19010
}, {
    "student_name": "Junior Mqadi",
    "email": "junior.mqadi@somewhere.com",
    "grade": 9,
    "section": null,
    "activity_date": "2016-11-08T22:00:00.000Z",
    "points": 26390
}, {
    "student_name": "Pearl Skosana",
    "email": "pearl.skosana@somewhere.com",
    "grade": 9,
    "section": null,
    "activity_date": "2016-10-27T22:00:00.000Z",
    "points": 4865
}, {
    "student_name": "Noluthando Mtsweni",
    "email": "noluthando.mtsweni@somewhere.com",
    "grade": 9,
    "section": null,
    "activity_date": "2016-10-27T22:00:00.000Z",
    "points": 8588
}, {
    "student_name": "Khanyisile Ntuli",
    "email": "khanyisile.ntuli@somewhere.com",
    "grade": 9,
    "section": null,
    "activity_date": "2016-11-08T22:00:00.000Z",
    "points": 9375
}, {
    "student_name": "Grace Sibiya",
    "email": "grace.sibiya@somewhere.com",
    "grade": 9,
    "section": null,
    "activity_date": "2016-11-08T22:00:00.000Z",
    "points": 15495
}, {
    "student_name": "Mbongeni Soko",
    "email": "mbongeni.soko@somewhere.com",
    "grade": 9,
    "section": null,
    "activity_date": "2016-11-08T22:00:00.000Z",
    "points": 6380
}, {
    "student_name": "Jabulile Sibeko",
    "email": "jabulile.sibeko@somewhere.com",
    "grade": 9,
    "section": null,
    "activity_date": "2016-10-27T22:00:00.000Z",
    "points": 17262
}, {
    "student_name": "Vuyelwa Mangethe",
    "email": "vuyelwa.mangethe@somewhere.com",
    "grade": 9,
    "section": null,
    "activity_date": "2016-10-27T22:00:00.000Z",
    "points": 56613
}, {
    "student_name": "Njabulo Mthunzi",
    "email": "njabulo.mthunzi@somewhere.com",
    "grade": 9,
    "section": null,
    "activity_date": "2016-11-08T22:00:00.000Z",
    "points": 10900
}, {
    "student_name": "Farai Zungu",
    "email": "farai.zungu@somewhere.com",
    "grade": 9,
    "section": null,
    "activity_date": "2016-11-20T22:00:00.000Z",
    "points": 14510
}, {
    "student_name": "Makie Nkabinde",
    "email": "makie.nkabinde@somewhere.com",
    "grade": 9,
    "section": null,
    "activity_date": "2016-11-08T22:00:00.000Z",
    "points": 76490
}, {
    "student_name": "Mbali Nhlapo",
    "email": "mbali.nhlapo@somewhere.com",
    "grade": 9,
    "section": null,
    "activity_date": "2016-09-07T22:00:00.000Z",
    "points": 3445
}, {
    "student_name": "Bheki Phama",
    "email": "bheki.phama@somewhere.com",
    "grade": 9,
    "section": null,
    "activity_date": "2016-11-08T22:00:00.000Z",
    "points": 4405
}, {
    "student_name": "Rethabile Mkhwanazi",
    "email": "rethabile.mkhwanazi@somewhere.com",
    "grade": 9,
    "section": null,
    "activity_date": "2016-10-30T22:00:00.000Z",
    "points": 40975
}, {
    "student_name": "Tebogo Ntlombeni",
    "email": "tebogo.ntlombeni@somewhere.com",
    "grade": 9,
    "section": null,
    "activity_date": "2016-11-20T22:00:00.000Z",
    "points": 45000
}, {
    "student_name": "Lebogang Chego",
    "email": "lebogang.chego@somewhere.com",
    "grade": 9,
    "section": null,
    "activity_date": "2016-11-16T22:00:00.000Z",
    "points": 39250
}, {
    "student_name": "Phumla Nyoni",
    "email": "phumla.nyoni@somewhere.com",
    "grade": 9,
    "section": null,
    "activity_date": "2016-11-20T22:00:00.000Z",
    "points": 18425
}, {
    "student_name": "Bongiwe Gama",
    "email": "bongiwe.gama@somewhere.com",
    "grade": 9,
    "section": null,
    "activity_date": "2016-10-27T22:00:00.000Z",
    "points": 31625
}, {
    "student_name": "Sipho Shongwe",
    "email": "sipho.shongwe@somewhere.com",
    "grade": 9,
    "section": null,
    "activity_date": "2016-09-07T22:00:00.000Z",
    "points": 1275
}, {
    "student_name": "Lindokuhle Mabena",
    "email": "lindokuhle.mabena@somewhere.com",
    "grade": 9,
    "section": null,
    "activity_date": "2016-11-20T22:00:00.000Z",
    "points": 36225
}, {
    "student_name": "Karabelo Mokoena",
    "email": "karabelo.mokoena@somewhere.com",
    "grade": 9,
    "section": null,
    "activity_date": "2016-11-20T22:00:00.000Z",
    "points": 10502
}, {
    "student_name": "Thando Ndimande",
    "email": "thando.ndimande@somewhere.com",
    "grade": 9,
    "section": null,
    "activity_date": "2016-11-08T22:00:00.000Z",
    "points": 26657
}, {
    "student_name": "Kabelo Skosana",
    "email": "kabelo.skosana@somewhere.com",
    "grade": 9,
    "section": null,
    "activity_date": "2016-11-08T22:00:00.000Z",
    "points": 42375
}, {
    "student_name": "Ntokozo Mhlangula",
    "email": "ntokozo.mhlangula@somewhere.com",
    "grade": 9,
    "section": null,
    "activity_date": "2016-11-08T22:00:00.000Z",
    "points": 49025
}, {
    "student_name": "Sphilelo Mhlongo",
    "email": "sphilelo.mhlongo@somewhere.com",
    "grade": 9,
    "section": null,
    "activity_date": "2016-11-20T22:00:00.000Z",
    "points": 19850
}, {
    "student_name": "Lebohang Motloenya",
    "email": "lebohang.motloenya@somewhere.com",
    "grade": 9,
    "section": null,
    "activity_date": "2016-11-20T22:00:00.000Z",
    "points": 85975
}, {
    "student_name": "Lindiwe Sibeko",
    "email": "lindiwe.sibeko@somewhere.com",
    "grade": 9,
    "section": null,
    "activity_date": "2016-10-27T22:00:00.000Z",
    "points": 41902
}, {
    "student_name": "Owethu Mngomezulu",
    "email": "owethu.mngomezulu@somewhere.com",
    "grade": 9,
    "section": null,
    "activity_date": "2016-11-20T22:00:00.000Z",
    "points": 47165
}, {
    "student_name": "Mamogo Molepo",
    "email": "mamogo.molepo@somewhere.com",
    "grade": 9,
    "section": null,
    "activity_date": "2016-11-08T22:00:00.000Z",
    "points": 19015
}, {
    "student_name": "Dineo Nhlengethwa",
    "email": "dineo.nhlengethwa@somewhere.com",
    "grade": 9,
    "section": null,
    "activity_date": "2016-10-27T22:00:00.000Z",
    "points": 42005
}, {
    "student_name": "Lindokuhle Tivane",
    "email": "lindokuhle.tivane@somewhere.com",
    "grade": 9,
    "section": null,
    "activity_date": "2016-10-27T22:00:00.000Z",
    "points": 13276
}, {
    "student_name": "Bongiwe Mdunusana",
    "email": "bongiwe.mdunusana@somewhere.com",
    "grade": 9,
    "section": null,
    "activity_date": "2016-11-20T22:00:00.000Z",
    "points": 21950
}, {
    "student_name": "Ntokozo Manana",
    "email": "ntokozo.manana@somewhere.com",
    "grade": 9,
    "section": null,
    "activity_date": "2016-10-26T22:00:00.000Z",
    "points": 11500
}, {
    "student_name": "Owethu Ralethata",
    "email": "owethu.ralethata@somewhere.com",
    "grade": 9,
    "section": null,
    "activity_date": "2016-10-27T22:00:00.000Z",
    "points": 10777
}, {
    "student_name": "Nokuphila Zwane",
    "email": "nokuphila.zwane@somewhere.com",
    "grade": 9,
    "section": null,
    "activity_date": "2016-11-08T22:00:00.000Z",
    "points": 7244
}, {
    "student_name": "Sibusiso Dube",
    "email": "sibusiso.dube@somewhere.com",
    "grade": 9,
    "section": null,
    "activity_date": "2016-11-08T22:00:00.000Z",
    "points": 2900
}, {
    "student_name": "Matshidiso Mahlangu",
    "email": "matshidiso.mahlangu@somewhere.com",
    "grade": 9,
    "section": null,
    "activity_date": "2016-11-20T22:00:00.000Z",
    "points": 4981
}, {
    "student_name": "Bonginkosi Masimula",
    "email": "bonginkosi.masimula@somewhere.com",
    "grade": 9,
    "section": null,
    "activity_date": "2016-11-20T22:00:00.000Z",
    "points": 7025
}, {
    "student_name": "Collen Sibeko",
    "email": "collen.sibeko@somewhere.com",
    "grade": 9,
    "section": null,
    "activity_date": "2016-11-08T22:00:00.000Z",
    "points": 27458
}, {
    "student_name": "Karabo Motene",
    "email": "karabo.motene@somewhere.com",
    "grade": 9,
    "section": null,
    "activity_date": "2016-11-08T22:00:00.000Z",
    "points": 6620
}, {
    "student_name": "Takatso Malapela",
    "email": "takatso.malapela@somewhere.com",
    "grade": 9,
    "section": null,
    "activity_date": "2016-10-27T22:00:00.000Z",
    "points": 8934
}, {
    "student_name": "Kgalalelo Moeketsi",
    "email": "kgalalelo.moeketsi@somewhere.com",
    "grade": 9,
    "section": null,
    "activity_date": "2016-10-27T22:00:00.000Z",
    "points": 18375
}, {
    "student_name": "Thando Mkhonza",
    "email": "thando.mkhonza@somewhere.com",
    "grade": 9,
    "section": null,
    "activity_date": "2016-11-08T22:00:00.000Z",
    "points": 4390
}, {
    "student_name": "Lerato Malinga",
    "email": "lerato.malinga@somewhere.com",
    "grade": 9,
    "section": null,
    "activity_date": "2016-11-08T22:00:00.000Z",
    "points": 82400
}, {
    "student_name": "Andile Vilakazi",
    "email": "andile.vilakazi@somewhere.com",
    "grade": 9,
    "section": null,
    "activity_date": "2016-10-27T22:00:00.000Z",
    "points": 5440
}, {
    "student_name": "Sphesihle Ngeu",
    "email": "sphesihle.ngeu@somewhere.com",
    "grade": 9,
    "section": null,
    "activity_date": "2016-11-20T22:00:00.000Z",
    "points": 13625
}, {
    "student_name": "Sphesihle Kubheka",
    "email": "sphesihle.kubheka@somewhere.com",
    "grade": 9,
    "section": null,
    "activity_date": "2016-11-08T22:00:00.000Z",
    "points": 4610
}, {
    "student_name": "Nosipho Khumalo",
    "email": "nosipho.khumalo@somewhere.com",
    "grade": 9,
    "section": null,
    "activity_date": "2016-11-08T22:00:00.000Z",
    "points": 9156
}, {
    "student_name": "Lubuto Mwape",
    "email": "lubuto.mwape@somewhere.com",
    "grade": 9,
    "section": null,
    "activity_date": "2016-11-08T22:00:00.000Z",
    "points": 22305
}, {
    "student_name": "Zandile Ntwakumba",
    "email": "zandile.ntwakumba@somewhere.com",
    "grade": 9,
    "section": null,
    "activity_date": "2016-09-07T22:00:00.000Z",
    "points": 20185
}, {
    "student_name": "Sakhilegr9 Mabena",
    "email": "sakhilegr9.mabena@somewhere.com",
    "grade": 9,
    "section": null,
    "activity_date": "2016-08-31T22:00:00.000Z",
    "points": 12976
}, {
    "student_name": "Zinhle Vilakazi",
    "email": "zinhle.vilakazi@somewhere.com",
    "grade": 9,
    "section": null,
    "activity_date": "2016-11-08T22:00:00.000Z",
    "points": 6025
}, {
    "student_name": "Andile Xabendleni",
    "email": "andile.xabendleni@somewhere.com",
    "grade": 9,
    "section": null,
    "activity_date": "2016-10-27T22:00:00.000Z",
    "points": 21625
}, {
    "student_name": "Triston Tsonye",
    "email": "triston.tsonye@somewhere.com",
    "grade": 9,
    "section": null,
    "activity_date": "2016-10-27T22:00:00.000Z",
    "points": 25560
}, {
    "student_name": "Nomvula Mkhosi",
    "email": "nomvula.mkhosi@somewhere.com",
    "grade": 9,
    "section": null,
    "activity_date": "2016-11-20T22:00:00.000Z",
    "points": 7385
}, {
    "student_name": "Mpho Mthonjeni",
    "email": "mpho.mthonjeni@somewhere.com",
    "grade": 9,
    "section": null,
    "activity_date": "2016-11-20T22:00:00.000Z",
    "points": 19060
}, {
    "student_name": "Ndumiso Masogana",
    "email": "ndumiso.masogana@somewhere.com",
    "grade": 9,
    "section": null,
    "activity_date": "2016-11-08T22:00:00.000Z",
    "points": 46850
}, {
    "student_name": "Andile Zikalala",
    "email": "andile.zikalala@somewhere.com",
    "grade": 9,
    "section": null,
    "activity_date": "2016-11-08T22:00:00.000Z",
    "points": 7206
}, {
    "student_name": "Naledi Mochadibane",
    "email": "naledi.mochadibane@somewhere.com",
    "grade": 9,
    "section": null,
    "activity_date": "2016-10-26T22:00:00.000Z",
    "points": 3931
}, {
    "student_name": "Refiloe Kope",
    "email": "refiloe.kope@somewhere.com",
    "grade": 9,
    "section": null,
    "activity_date": "2016-11-20T22:00:00.000Z",
    "points": 37542
}, {
    "student_name": "Lunga Nkosi",
    "email": "lunga.nkosi@somewhere.com",
    "grade": 9,
    "section": null,
    "activity_date": "2016-11-08T22:00:00.000Z",
    "points": 9400
}, {
    "student_name": "Sibusiso Mamba",
    "email": "sibusiso.mamba@somewhere.com",
    "grade": 9,
    "section": null,
    "activity_date": "2016-11-08T22:00:00.000Z",
    "points": 5380
}, {
    "student_name": "Tshepang Mabena",
    "email": "tshepang.mabena@somewhere.com",
    "grade": 9,
    "section": null,
    "activity_date": "2016-11-20T22:00:00.000Z",
    "points": 26238
}, {
    "student_name": "Bongani Ndlovu",
    "email": "bongani.ndlovu@somewhere.com",
    "grade": 9,
    "section": null,
    "activity_date": "2016-11-08T22:00:00.000Z",
    "points": 10905
}, {
    "student_name": "Noxolo Mthethwa",
    "email": "noxolo.mthethwa@somewhere.com",
    "grade": 9,
    "section": null,
    "activity_date": "2016-10-27T22:00:00.000Z",
    "points": 5400
}, {
    "student_name": "Nompumelelo Mahlangu",
    "email": "nompumelelo.mahlangu@somewhere.com",
    "grade": 9,
    "section": null,
    "activity_date": "2016-11-08T22:00:00.000Z",
    "points": 3260
}, {
    "student_name": "Kamohelo Sibande",
    "email": "kamohelo.sibande@somewhere.com",
    "grade": 9,
    "section": null,
    "activity_date": "2016-10-27T22:00:00.000Z",
    "points": 8675
}, {
    "student_name": "Noluthando Nyaweni",
    "email": "noluthando.nyaweni@somewhere.com",
    "grade": 9,
    "section": null,
    "activity_date": "2016-11-20T22:00:00.000Z",
    "points": 3656
}, {
    "student_name": "Mpho Mokoena",
    "email": "mpho.mokoena@somewhere.com",
    "grade": 9,
    "section": null,
    "activity_date": "2016-08-09T22:00:00.000Z",
    "points": 1120
}, {
    "student_name": "Bongiwe Dludlu",
    "email": "bongiwe.dludlu@somewhere.com",
    "grade": 9,
    "section": null,
    "activity_date": "2016-10-27T22:00:00.000Z",
    "points": 19375
}, {
    "student_name": "Thapelo Tsotetsi",
    "email": "thapelo.tsotetsi@somewhere.com",
    "grade": 9,
    "section": null,
    "activity_date": "2016-10-26T22:00:00.000Z",
    "points": 3675
}, {
    "student_name": "Thobile Msiza",
    "email": "thobile.msiza@somewhere.com",
    "grade": 9,
    "section": null,
    "activity_date": "2016-10-27T22:00:00.000Z",
    "points": 2221
}, {
    "student_name": "Tshepiso Mahlangu",
    "email": "tshepiso.mahlangu@somewhere.com",
    "grade": 9,
    "section": null,
    "activity_date": "2016-10-27T22:00:00.000Z",
    "points": 3695
}, {
    "student_name": "Nomsa Tsotetsi",
    "email": "nomsa.tsotetsi@somewhere.com",
    "grade": 9,
    "section": null,
    "activity_date": "2016-11-20T22:00:00.000Z",
    "points": 7800
}, {
    "student_name": "Gugu Dibakoane",
    "email": "gugu.dibakoane@somewhere.com",
    "grade": 9,
    "section": null,
    "activity_date": "2016-10-26T22:00:00.000Z",
    "points": 3318
}, {
    "student_name": "Ntokozo Maduna",
    "email": "ntokozo.maduna@somewhere.com",
    "grade": 9,
    "section": null,
    "activity_date": "2016-11-08T22:00:00.000Z",
    "points": 24075
}, {
    "student_name": "Lerato Motshabi",
    "email": "lerato.motshabi@somewhere.com",
    "grade": 9,
    "section": null,
    "activity_date": "2016-11-08T22:00:00.000Z",
    "points": 18040
}, {
    "student_name": "Ntokozo Msiza",
    "email": "ntokozo.msiza@somewhere.com",
    "grade": 9,
    "section": null,
    "activity_date": "2016-10-27T22:00:00.000Z",
    "points": 7285
}, {
    "student_name": "Itumeleng Makhoba",
    "email": "itumeleng.makhoba@somewhere.com",
    "grade": 9,
    "section": null,
    "activity_date": "2016-11-20T22:00:00.000Z",
    "points": 35165
}, {
    "student_name": "Lerato Mothibedi",
    "email": "lerato.mothibedi@somewhere.com",
    "grade": 9,
    "section": null,
    "activity_date": "2016-11-08T22:00:00.000Z",
    "points": 1400
}, {
    "student_name": "Karabo Tivane",
    "email": "karabo.tivane@somewhere.com",
    "grade": 0,
    "section": null,
    "activity_date": "2016-11-10T22:00:00.000Z",
    "points": 28990
}, {
    "student_name": "Noluthando Bulose",
    "email": "noluthando.bulose@somewhere.com",
    "grade": 0,
    "section": null,
    "activity_date": "2016-11-10T22:00:00.000Z",
    "points": 16470
}, {
    "student_name": "Nandipha Skosana",
    "email": "nandipha.skosana@somewhere.com",
    "grade": 0,
    "section": null,
    "activity_date": "2016-11-10T22:00:00.000Z",
    "points": 17245
}, {
    "student_name": "Tshiamo Mashinini",
    "email": "tshiamo.mashinini@somewhere.com",
    "grade": 0,
    "section": null,
    "activity_date": "2016-11-10T22:00:00.000Z",
    "points": 15075
}, {
    "student_name": "Keabetsoe Mahlangu",
    "email": "keabetsoe.mahlangu@somewhere.com",
    "grade": 0,
    "section": null,
    "activity_date": "2016-11-10T22:00:00.000Z",
    "points": 18500
}, {
    "student_name": "Kagiso Molefe",
    "email": "kagiso.molefe@somewhere.com",
    "grade": 0,
    "section": null,
    "activity_date": "2016-11-10T22:00:00.000Z",
    "points": 13790
}, {
    "student_name": "Kgalalelo Tshabalala",
    "email": "kgalalelo.tshabalala@somewhere.com",
    "grade": 0,
    "section": null,
    "activity_date": "2016-11-09T22:00:00.000Z",
    "points": 11125
}, {
    "student_name": "Elona Ndzambo",
    "email": "elona.ndzambo@somewhere.com",
    "grade": 0,
    "section": null,
    "activity_date": "2016-11-10T22:00:00.000Z",
    "points": 22170
}, {
    "student_name": "Boitumelo Ngwenya",
    "email": "boitumelo.ngwenya@somewhere.com",
    "grade": 0,
    "section": null,
    "activity_date": "2016-11-09T22:00:00.000Z",
    "points": 14875
}, {
    "student_name": "Njabulo Mkhatshwa",
    "email": "njabulo.mkhatshwa@somewhere.com",
    "grade": 0,
    "section": null,
    "activity_date": "2016-11-10T22:00:00.000Z",
    "points": 20415
}, {
    "student_name": "Nkosana Ndati",
    "email": "nkosana.ndati@somewhere.com",
    "grade": 0,
    "section": null,
    "activity_date": "2016-11-09T22:00:00.000Z",
    "points": 14700
}, {
    "student_name": "Tokelo Tleane",
    "email": "tokelo.tleane@somewhere.com",
    "grade": 0,
    "section": null,
    "activity_date": "2016-11-10T22:00:00.000Z",
    "points": 29121
}, {
    "student_name": "Thulani Nkosi",
    "email": "thulani.nkosi@somewhere.com",
    "grade": 0,
    "section": null,
    "activity_date": "2016-11-10T22:00:00.000Z",
    "points": 26250
}, {
    "student_name": "Palesa Khaile",
    "email": "palesa.khaile@somewhere.com",
    "grade": 0,
    "section": null,
    "activity_date": "2016-11-17T22:00:00.000Z",
    "points": 48265
}, {
    "student_name": "Thando Nhlapho",
    "email": "thando.nhlapho@somewhere.com",
    "grade": 0,
    "section": null,
    "activity_date": "2016-11-10T22:00:00.000Z",
    "points": 20750
}, {
    "student_name": "Pheelo Mabuza",
    "email": "pheelo.mabuza@somewhere.com",
    "grade": 0,
    "section": null,
    "activity_date": "2016-11-10T22:00:00.000Z",
    "points": 12505
}, {
    "student_name": "Zama Vandemerwe",
    "email": "zama.vandemerwe@somewhere.com",
    "grade": 0,
    "section": null,
    "activity_date": "2016-11-17T22:00:00.000Z",
    "points": 14930
}, {
    "student_name": "Samukelo Mahlaba",
    "email": "samukelo.mahlaba@somewhere.com",
    "grade": 0,
    "section": null,
    "activity_date": "2016-11-17T22:00:00.000Z",
    "points": 18350
}, {
    "student_name": "Koketso Molefe",
    "email": "koketso.molefe@somewhere.com",
    "grade": 0,
    "section": null,
    "activity_date": "2016-11-12T22:00:00.000Z",
    "points": 24090
}, {
    "student_name": "Mapule Thabethe",
    "email": "mapule.thabethe@somewhere.com",
    "grade": 0,
    "section": null,
    "activity_date": "2016-11-10T22:00:00.000Z",
    "points": 8950
}, {
    "student_name": "Kelello Kgwedi",
    "email": "kelello.kgwedi@somewhere.com",
    "grade": 0,
    "section": null,
    "activity_date": "2016-11-17T22:00:00.000Z",
    "points": 17355
}, {
    "student_name": "Mbali Dladla",
    "email": "mbali.dladla@somewhere.com",
    "grade": 0,
    "section": null,
    "activity_date": "2016-11-10T22:00:00.000Z",
    "points": 27935
}, {
    "student_name": "Lungelo Phuthi",
    "email": "lungelo.phuthi@somewhere.com",
    "grade": 0,
    "section": null,
    "activity_date": "2016-11-10T22:00:00.000Z",
    "points": 15455
}, {
    "student_name": "Hlengiwe Vilakazi",
    "email": "hlengiwe.vilakazi@somewhere.com",
    "grade": 0,
    "section": null,
    "activity_date": "2016-11-10T22:00:00.000Z",
    "points": 10340
}, {
    "student_name": "Kgaugelo Ngwenya",
    "email": "kgaugelo.ngwenya@somewhere.com",
    "grade": 0,
    "section": null,
    "activity_date": "2016-11-10T22:00:00.000Z",
    "points": 30150
}, {
    "student_name": "Natasha Mathe",
    "email": "natasha.mathe@somewhere.com",
    "grade": 0,
    "section": null,
    "activity_date": "2016-12-06T22:00:00.000Z",
    "points": 23815
}, {
    "student_name": "Ntokozo Masilela",
    "email": "ntokozo.masilela@somewhere.com",
    "grade": 0,
    "section": null,
    "activity_date": "2016-11-17T22:00:00.000Z",
    "points": 36215
}, {
    "student_name": "Thabiso Chego",
    "email": "thabiso.chego@somewhere.com",
    "grade": 0,
    "section": null,
    "activity_date": "2016-11-10T22:00:00.000Z",
    "points": 31500
}, {
    "student_name": "Xolani Maphanga",
    "email": "xolani.maphanga@somewhere.com",
    "grade": 0,
    "section": null,
    "activity_date": "2016-11-09T22:00:00.000Z",
    "points": 15430
}, {
    "student_name": "Dineo Vilakazi",
    "email": "dineo.vilakazi@somewhere.com",
    "grade": 0,
    "section": null,
    "activity_date": "2016-11-09T22:00:00.000Z",
    "points": 14740
}, {
    "student_name": "Zandile Mncube",
    "email": "zandile.mncube@somewhere.com",
    "grade": 0,
    "section": null,
    "activity_date": "2016-11-10T22:00:00.000Z",
    "points": 33425
}, {
    "student_name": "Ntokozo Dlamini",
    "email": "ntokozo.dlamini@somewhere.com",
    "grade": 0,
    "section": null,
    "activity_date": "2016-11-11T22:00:00.000Z",
    "points": 19950
}, {
    "student_name": "Khaya Mbatha",
    "email": "khaya.mbatha@somewhere.com",
    "grade": 0,
    "section": null,
    "activity_date": "2016-11-10T22:00:00.000Z",
    "points": 26689
}, {
    "student_name": "Portia Morapa",
    "email": "portia.morapa@somewhere.com",
    "grade": 0,
    "section": null,
    "activity_date": "2016-11-17T22:00:00.000Z",
    "points": 27070
}, {
    "student_name": "Siphesihle Zwane",
    "email": "siphesihle.zwane@somewhere.com",
    "grade": 0,
    "section": null,
    "activity_date": "2016-11-10T22:00:00.000Z",
    "points": 26075
}, {
    "student_name": "Sifiso Magona",
    "email": "sifiso.magona@somewhere.com",
    "grade": 0,
    "section": null,
    "activity_date": "2016-11-10T22:00:00.000Z",
    "points": 19005
}, {
    "student_name": "Amanda Seshane",
    "email": "amanda.seshane@somewhere.com",
    "grade": 0,
    "section": null,
    "activity_date": "2016-11-10T22:00:00.000Z",
    "points": 18090
}, {
    "student_name": "Ayanda Juqu",
    "email": "ayanda.juqu@somewhere.com",
    "grade": 0,
    "section": null,
    "activity_date": "2016-11-10T22:00:00.000Z",
    "points": 31725
}, {
    "student_name": "Jessica Harper",
    "email": "jessica.harper@somewhere.com",
    "grade": 0,
    "section": null,
    "activity_date": "2016-11-10T22:00:00.000Z",
    "points": 14485
}, {
    "student_name": "Cromwell Nyamapfeni",
    "email": "cromwell.nyamapfeni@somewhere.com",
    "grade": 0,
    "section": null,
    "activity_date": "2016-11-17T22:00:00.000Z",
    "points": 28270
}, {
    "student_name": "Katlego Gazide",
    "email": "katlego.gazide@somewhere.com",
    "grade": 0,
    "section": null,
    "activity_date": "2016-11-09T22:00:00.000Z",
    "points": 15900
}, {
    "student_name": "Siyolisiwe Buqindlela",
    "email": "siyolisiwe.buqindlela@somewhere.com",
    "grade": 0,
    "section": null,
    "activity_date": "2016-11-17T22:00:00.000Z",
    "points": 16465
}, {
    "student_name": "Simphiwe Moloi",
    "email": "simphiwe.moloi@somewhere.com",
    "grade": 0,
    "section": null,
    "activity_date": "2016-11-17T22:00:00.000Z",
    "points": 25450
}, {
    "student_name": "Yanga Mphayisa",
    "email": "yanga.mphayisa@somewhere.com",
    "grade": 0,
    "section": null,
    "activity_date": "2016-11-10T22:00:00.000Z",
    "points": 23150
}, {
    "student_name": "Dineo Mohlaping",
    "email": "dineo.mohlaping@somewhere.com",
    "grade": 0,
    "section": null,
    "activity_date": "2016-11-17T22:00:00.000Z",
    "points": 9735
}, {
    "student_name": "Mogau Ntobeng",
    "email": "mogau.ntobeng@somewhere.com",
    "grade": 0,
    "section": null,
    "activity_date": "2016-11-17T22:00:00.000Z",
    "points": 50875
}, {
    "student_name": "Nonkazimulo Nkosi",
    "email": "nonkazimulo.nkosi@somewhere.com",
    "grade": 0,
    "section": null,
    "activity_date": "2016-11-17T22:00:00.000Z",
    "points": 11580
}, {
    "student_name": "Paseka Manyika",
    "email": "paseka.manyika@somewhere.com",
    "grade": 0,
    "section": null,
    "activity_date": "2016-11-09T22:00:00.000Z",
    "points": 21150
}, {
    "student_name": "Nomathamsanqa Wesaba",
    "email": "nomathamsanqa.wesaba@somewhere.com",
    "grade": 0,
    "section": null,
    "activity_date": "2016-11-10T22:00:00.000Z",
    "points": 15975
}, {
    "student_name": "Nelisiwe Gwebu",
    "email": "nelisiwe.gwebu@somewhere.com",
    "grade": 0,
    "section": null,
    "activity_date": "2016-11-08T22:00:00.000Z",
    "points": 11100
}, {
    "student_name": "Sthembile Makhonjwa",
    "email": "sthembile.makhonjwa@somewhere.com",
    "grade": 0,
    "section": null,
    "activity_date": "2016-11-10T22:00:00.000Z",
    "points": 21100
}, {
    "student_name": "Khensani Tshabalala",
    "email": "khensani.tshabalala@somewhere.com",
    "grade": 0,
    "section": null,
    "activity_date": "2016-11-09T22:00:00.000Z",
    "points": 25120
}, {
    "student_name": "Khensani Vilakazi",
    "email": "khensani.vilakazi@somewhere.com",
    "grade": 0,
    "section": null,
    "activity_date": "2016-11-10T22:00:00.000Z",
    "points": 34595
}, {
    "student_name": "Nandi Nkosi",
    "email": "nandi.nkosi@somewhere.com",
    "grade": 0,
    "section": null,
    "activity_date": "2016-11-10T22:00:00.000Z",
    "points": 14550
}, {
    "student_name": "Karabo Thabethe",
    "email": "karabo.thabethe@somewhere.com",
    "grade": 0,
    "section": null,
    "activity_date": "2016-11-10T22:00:00.000Z",
    "points": 44140
}, {
    "student_name": "Lesego Matlou",
    "email": "lesego.matlou@somewhere.com",
    "grade": 0,
    "section": null,
    "activity_date": "2016-11-10T22:00:00.000Z",
    "points": 16410
}, {
    "student_name": "Andisiwe Nxiba",
    "email": "andisiwe.nxiba@somewhere.com",
    "grade": 0,
    "section": null,
    "activity_date": "2016-11-10T22:00:00.000Z",
    "points": 26395
}, {
    "student_name": "Lebo Hlophe",
    "email": "lebo.hlophe@somewhere.com",
    "grade": 0,
    "section": null,
    "activity_date": "2016-11-10T22:00:00.000Z",
    "points": 39485
}, {
    "student_name": "Kamogelo Mnqosini",
    "email": "kamogelo.mnqosini@somewhere.com",
    "grade": 0,
    "section": null,
    "activity_date": "2016-11-09T22:00:00.000Z",
    "points": 11320
}, {
    "student_name": "Princess Agu",
    "email": "princess.agu@somewhere.com",
    "grade": 0,
    "section": null,
    "activity_date": "2016-11-10T22:00:00.000Z",
    "points": 15845
}, {
    "student_name": "Lethabo Ngake",
    "email": "lethabo.ngake@somewhere.com",
    "grade": 0,
    "section": null,
    "activity_date": "2016-11-10T22:00:00.000Z",
    "points": 15500
}, {
    "student_name": "Lesego Letsoalo",
    "email": "lesego.letsoalo@somewhere.com",
    "grade": 0,
    "section": null,
    "activity_date": "2016-11-17T22:00:00.000Z",
    "points": 58775
}, {
    "student_name": "Mpho Mogare",
    "email": "mpho.mogare@somewhere.com",
    "grade": 0,
    "section": null,
    "activity_date": "2016-11-10T22:00:00.000Z",
    "points": 34280
}, {
    "student_name": "Omphile Manare",
    "email": "omphile.manare@somewhere.com",
    "grade": 0,
    "section": null,
    "activity_date": "2016-11-10T22:00:00.000Z",
    "points": 22450
}, {
    "student_name": "Samukelo Mabena",
    "email": "samukelo.mabena@somewhere.com",
    "grade": 0,
    "section": null,
    "activity_date": "2016-11-10T22:00:00.000Z",
    "points": 17700
}, {
    "student_name": "Richard Malinga",
    "email": "richard.malinga@somewhere.com",
    "grade": 0,
    "section": null,
    "activity_date": "2016-11-10T22:00:00.000Z",
    "points": 13475
}, {
    "student_name": "Ayanda Masinga",
    "email": "ayanda.masinga@somewhere.com",
    "grade": 0,
    "section": null,
    "activity_date": "2016-11-10T22:00:00.000Z",
    "points": 20925
}, {
    "student_name": "Phumelele Cimela",
    "email": "phumelele.cimela@somewhere.com",
    "grade": 0,
    "section": null,
    "activity_date": "2016-11-10T22:00:00.000Z",
    "points": 28350
}, {
    "student_name": "Siphesihle Msiza",
    "email": "siphesihle.msiza@somewhere.com",
    "grade": 0,
    "section": null,
    "activity_date": "2016-11-10T22:00:00.000Z",
    "points": 15325
}, {
    "student_name": "Nomvuselelo Mathebula",
    "email": "nomvuselelo.mathebula@somewhere.com",
    "grade": 0,
    "section": null,
    "activity_date": "2016-11-17T22:00:00.000Z",
    "points": 30850
}, {
    "student_name": "Nondumiso Wambi",
    "email": "nondumiso.wambi@somewhere.com",
    "grade": 0,
    "section": null,
    "activity_date": "2016-12-01T22:00:00.000Z",
    "points": 16635
}, {
    "student_name": "Kekeletso Moshane",
    "email": "kekeletso.moshane@somewhere.com",
    "grade": 0,
    "section": null,
    "activity_date": "2016-11-09T22:00:00.000Z",
    "points": 8650
}, {
    "student_name": "Natasha Nkosi",
    "email": "natasha.nkosi@somewhere.com",
    "grade": 0,
    "section": null,
    "activity_date": "2016-11-10T22:00:00.000Z",
    "points": 13625
}, {
    "student_name": "Palesa Ndlovu",
    "email": "palesa.ndlovu@somewhere.com",
    "grade": 0,
    "section": null,
    "activity_date": "2016-11-10T22:00:00.000Z",
    "points": 30505
}, {
    "student_name": "Nompumelelo Mkhize",
    "email": "nompumelelo.mkhize@somewhere.com",
    "grade": 0,
    "section": null,
    "activity_date": "2016-11-10T22:00:00.000Z",
    "points": 15100
}, {
    "student_name": "Dineo Rantsane",
    "email": "dineo.rantsane@somewhere.com",
    "grade": 0,
    "section": null,
    "activity_date": "2016-11-09T22:00:00.000Z",
    "points": 12200
}, {
    "student_name": "Luthando Bali",
    "email": "luthando.bali@somewhere.com",
    "grade": 0,
    "section": null,
    "activity_date": "2016-11-17T22:00:00.000Z",
    "points": 13805
}, {
    "student_name": "Mabandla Simelane",
    "email": "mabandla.simelane@somewhere.com",
    "grade": 0,
    "section": null,
    "activity_date": "2016-11-10T22:00:00.000Z",
    "points": 11920
}, {
    "student_name": "Esona Sikweza",
    "email": "esona.sikweza@somewhere.com",
    "grade": 0,
    "section": null,
    "activity_date": "2016-11-17T22:00:00.000Z",
    "points": 22480
}, {
    "student_name": "Sibongile Ramovha",
    "email": "sibongile.ramovha@somewhere.com",
    "grade": 0,
    "section": null,
    "activity_date": "2016-11-12T22:00:00.000Z",
    "points": 21575
}, {
    "student_name": "Hopolang Tshabalala",
    "email": "hopolang.tshabalala@somewhere.com",
    "grade": 0,
    "section": null,
    "activity_date": "2016-11-08T22:00:00.000Z",
    "points": 15825
}, {
    "student_name": "Lorna Nkosi",
    "email": "lorna.nkosi@somewhere.com",
    "grade": 0,
    "section": null,
    "activity_date": "2016-11-10T22:00:00.000Z",
    "points": 9760
}, {
    "student_name": "Wandile Mahlangu",
    "email": "wandile.mahlangu@somewhere.com",
    "grade": 0,
    "section": null,
    "activity_date": "2016-11-10T22:00:00.000Z",
    "points": 35550
}, {
    "student_name": "Philani Bukhali",
    "email": "philani.bukhali@somewhere.com",
    "grade": 0,
    "section": null,
    "activity_date": "2016-11-10T22:00:00.000Z",
    "points": 15850
}, {
    "student_name": "Nosipho Ndlamlenze",
    "email": "nosipho.ndlamlenze@somewhere.com",
    "grade": 0,
    "section": null,
    "activity_date": "2016-11-10T22:00:00.000Z",
    "points": 24485
}, {
    "student_name": "Lesedi Moloko",
    "email": "lesedi.moloko@somewhere.com",
    "grade": 0,
    "section": null,
    "activity_date": "2016-11-10T22:00:00.000Z",
    "points": 11015
}, {
    "student_name": "Uthimna Mahlangu",
    "email": "uthimna.mahlangu@somewhere.com",
    "grade": 0,
    "section": null,
    "activity_date": "2016-12-01T22:00:00.000Z",
    "points": 52930
}, {
    "student_name": "Unathi Hlumbane",
    "email": "unathi.hlumbane@somewhere.com",
    "grade": 0,
    "section": null,
    "activity_date": "2016-11-10T22:00:00.000Z",
    "points": 17425
}, {
    "student_name": "Violet Mhlongo",
    "email": "violet.mhlongo@somewhere.com",
    "grade": 0,
    "section": null,
    "activity_date": "2016-11-10T22:00:00.000Z",
    "points": 43515
}, {
    "student_name": "Sandile Xaba",
    "email": "sandile.xaba@somewhere.com",
    "grade": 0,
    "section": null,
    "activity_date": "2016-11-10T22:00:00.000Z",
    "points": 14625
}, {
    "student_name": "Dimpho Zulu",
    "email": "dimpho.zulu@somewhere.com",
    "grade": 0,
    "section": null,
    "activity_date": "2016-11-10T22:00:00.000Z",
    "points": 17010
}, {
    "student_name": "Pamela Ngwana",
    "email": "pamela.ngwana@somewhere.com",
    "grade": 0,
    "section": null,
    "activity_date": "2016-11-10T22:00:00.000Z",
    "points": 10950
}, {
    "student_name": "Theluthando Sithole",
    "email": "theluthando.sithole@somewhere.com",
    "grade": 0,
    "section": null,
    "activity_date": "2016-11-09T22:00:00.000Z",
    "points": 19255
}, {
    "student_name": "Nkosinathi Mkabane",
    "email": "nkosinathi.mkabane@somewhere.com",
    "grade": 0,
    "section": null,
    "activity_date": "2016-11-10T22:00:00.000Z",
    "points": 75050
}, {
    "student_name": "Nompumelelo Molwana",
    "email": "nompumelelo.molwana@somewhere.com",
    "grade": 0,
    "section": null,
    "activity_date": "2016-11-09T22:00:00.000Z",
    "points": 32210
}, {
    "student_name": "Neo Moraba",
    "email": "neo.moraba@somewhere.com",
    "grade": 0,
    "section": null,
    "activity_date": "2016-11-10T22:00:00.000Z",
    "points": 16810
}, {
    "student_name": "Nokukhanya Nqeketo",
    "email": "nokukhanya.nqeketo@somewhere.com",
    "grade": 0,
    "section": null,
    "activity_date": "2016-11-10T22:00:00.000Z",
    "points": 19440
}, {
    "student_name": "Teboho Tsotetsi",
    "email": "teboho.tsotetsi@somewhere.com",
    "grade": 0,
    "section": null,
    "activity_date": "2016-11-10T22:00:00.000Z",
    "points": 8035
}, {
    "student_name": "Bonakele Zulu",
    "email": "bonakele.zulu@somewhere.com",
    "grade": 0,
    "section": null,
    "activity_date": "2016-11-10T22:00:00.000Z",
    "points": 22485
}, {
    "student_name": "Princess Mahlangu",
    "email": "princess.mahlangu@somewhere.com",
    "grade": 0,
    "section": null,
    "activity_date": "2016-11-10T22:00:00.000Z",
    "points": 30870
}, {
    "student_name": "Musawenkosi Madonsela",
    "email": "musawenkosi.madonsela@somewhere.com",
    "grade": 0,
    "section": null,
    "activity_date": "2016-11-10T22:00:00.000Z",
    "points": 6300
}]
